odoo8_addon_business_requirement_from_support-8.0.1.0.0-py2.7-nspkg.pth
odoo8_addon_business_requirement_from_support-8.0.1.0.0.dist-info/DESCRIPTION.rst
odoo8_addon_business_requirement_from_support-8.0.1.0.0.dist-info/METADATA
odoo8_addon_business_requirement_from_support-8.0.1.0.0.dist-info/RECORD
odoo8_addon_business_requirement_from_support-8.0.1.0.0.dist-info/WHEEL
odoo8_addon_business_requirement_from_support-8.0.1.0.0.dist-info/metadata.json
odoo8_addon_business_requirement_from_support-8.0.1.0.0.dist-info/namespace_packages.txt
odoo8_addon_business_requirement_from_support-8.0.1.0.0.dist-info/top_level.txt
odoo_addons/business_requirement_from_support/README.rst
odoo_addons/business_requirement_from_support/__init__.py
odoo_addons/business_requirement_from_support/__openerp__.py
odoo_addons/business_requirement_from_support/models/__init__.py
odoo_addons/business_requirement_from_support/models/business.py
odoo_addons/business_requirement_from_support/models/project_issue.py
odoo_addons/business_requirement_from_support/static/description/icon.png
odoo_addons/business_requirement_from_support/views/business_requirement.xml
odoo_addons/business_requirement_from_support/views/project_issue.xml
odoo_addons/business_requirement_from_support/wizard/__init__.py
odoo_addons/business_requirement_from_support/wizard/br_from_issue_view.xml
odoo_addons/business_requirement_from_support/wizard/br_issue.py
