Metadata-Version: 2.0
Name: odoo8-addon-business-requirement-from-support
Version: 8.0.1.0.0
Summary: Generate Business Requirements from issues
Home-page: https://www.praxya.com/
Author: Rubén Cabrera Martínez, Praxya, Odoo Community Association (OCA), 
Author-email: support@odoo-community.org
License: AGPL-3
Platform: UNKNOWN
Classifier: Programming Language :: Python :: 2.7
Classifier: Framework :: Odoo
Classifier: License :: OSI Approved :: GNU Affero General Public License v3
Requires-Dist: odoo (<9.0a,>=8.0a)
Requires-Dist: odoo8-addon-business-requirement
